pytest_aiohttp_client.py
pytest_aiohttp_client-0.1.0.dist-info/entry_points.txt
pytest_aiohttp_client-0.1.0.dist-info/METADATA
pytest_aiohttp_client-0.1.0.dist-info/LICENSE
pytest_aiohttp_client-0.1.0.dist-info/WHEEL
pytest_aiohttp_client-0.1.0.dist-info/RECORD
