Metadata-Version: 2.1
Name: pytest-aiohttp-client
Version: 0.1.0
Summary: Pytest `client` fixture for the Aiohttp
Home-page: https://github.com/sivakov512/pytest-aiohttp-client
License: MIT
Author: Nikita Sivakov
Author-email: sivakov512@icloud.com
Requires-Python: >=3.9,<4.0
Classifier: License :: OSI Approved :: MIT License
Classifier: Programming Language :: Python :: 3
Classifier: Programming Language :: Python :: 3.9
Classifier: Programming Language :: Python :: 3.10
Classifier: Programming Language :: Python :: 3.11
Requires-Dist: aiohttp (>=3.8.3,<4.0.0)
Requires-Dist: pytest (>=7.2.0,<8.0.0)
Project-URL: Repository, https://github.com/sivakov512/pytest-aiohttp-client
